setup.py
topsis_yash/__init__.py
topsis_yash.egg-info/PKG-INFO
topsis_yash.egg-info/SOURCES.txt
topsis_yash.egg-info/dependency_links.txt
topsis_yash.egg-info/requires.txt
topsis_yash.egg-info/top_level.txt