Metadata-Version: 1.1
Name: topsis-yash
Version: 0.0.0
Summary: A tool to calculate TOPSIS Score and Rank for given Dataset.
Home-page: UNKNOWN
Author: Yash Shukla
Author-email: yash981815@gmail.com
License: UNKNOWN
Keywords: topsis calculator
Platform: UNKNOWN
Classifier: Development Status :: 5 - Production/Stable
Classifier: Intended Audience :: Education
Classifier: Operating System :: Microsoft :: Windows :: Windows 10
Classifier: License :: OSI Approved :: MIT License
Classifier: Programming Language :: Python :: 3
